postgresql_auth/__init__.py
postgresql_auth/postgresql_auth.py
5x_postgresql_auth_manager-0.1.0.dist-info/METADATA
5x_postgresql_auth_manager-0.1.0.dist-info/WHEEL
5x_postgresql_auth_manager-0.1.0.dist-info/top_level.txt
5x_postgresql_auth_manager-0.1.0.dist-info/RECORD
