Metadata-Version: 2.4
Name: 5x-postgresql-auth-manager
Version: 0.1.0
Summary: A package to manage PostgreSQL connections using environment variables.
Home-page: https://github.com/your-org/5x-postgresql-auth-manager
Author: Your Name
Author-email: your.email@example.com
Classifier: Programming Language :: Python :: 3
Classifier: License :: OSI Approved :: MIT License
Classifier: Operating System :: OS Independent
Requires-Python: >=3.6
Requires-Dist: psycopg2-binary>=2.9.0
Dynamic: author
Dynamic: author-email
Dynamic: classifier
Dynamic: description
Dynamic: description-content-type
Dynamic: home-page
Dynamic: requires-dist
Dynamic: requires-python
Dynamic: summary
